__init__.py
fmu/__init__.py
fmu/sim2seis/__init__.py
fmu/sim2seis/version.py
fmu/sim2seis/cleanup/__init__.py
fmu/sim2seis/cleanup/__main__.py
fmu/sim2seis/forward_models/__init__.py
fmu/sim2seis/forward_models/sim2seis_cleanup.py
fmu/sim2seis/forward_models/sim2seis_map_attribute.py
fmu/sim2seis/forward_models/sim2seis_observed_data.py
fmu/sim2seis/forward_models/sim2seis_relative_inversion.py
fmu/sim2seis/forward_models/sim2seis_seismic_forward.py
fmu/sim2seis/hook_implementations/__init__.py
fmu/sim2seis/hook_implementations/jobs.py
fmu/sim2seis/map_attributes/__init__.py
fmu/sim2seis/map_attributes/__main__.py
fmu/sim2seis/map_attributes/_dump_results.py
fmu/sim2seis/map_attributes/_retrieve_results.py
fmu/sim2seis/observed_data/__init__.py
fmu/sim2seis/observed_data/__main__.py
fmu/sim2seis/observed_data/_dump_results.py
fmu/sim2seis/observed_data/depth_convert_observed_data.py
fmu/sim2seis/observed_data/depth_surf.py
fmu/sim2seis/observed_data/import_time_data.py
fmu/sim2seis/observed_data/symlink.py
fmu/sim2seis/seismic_fwd/__init__.py
fmu/sim2seis/seismic_fwd/__main__.py
fmu/sim2seis/seismic_fwd/_dump_results.py
fmu/sim2seis/seismic_fwd/seismic_diff.py
fmu/sim2seis/seismic_fwd/seismic_forward.py
fmu/sim2seis/seismic_inversion/__init__.py
fmu/sim2seis/seismic_inversion/__main__.py
fmu/sim2seis/seismic_inversion/_dump_results.py
fmu/sim2seis/seismic_inversion/_retrieve_results.py
fmu/sim2seis/seismic_inversion/depth_convert_rel_ai.py
fmu/sim2seis/seismic_inversion/relative_seismic_inversion.py
fmu/sim2seis/seismic_inversion/simpli_4d_inversion.py
fmu/sim2seis/utilities/__init__.py
fmu/sim2seis/utilities/argument_parser.py
fmu/sim2seis/utilities/dump_results.py
fmu/sim2seis/utilities/export_with_dataio.py
fmu/sim2seis/utilities/get_yaml_file.py
fmu/sim2seis/utilities/interval_parser.py
fmu/sim2seis/utilities/libgeneral.py
fmu/sim2seis/utilities/libseis.py
fmu/sim2seis/utilities/obs_data_config_validation.py
fmu/sim2seis/utilities/seis_diff_dates.py
fmu_sim2seis-0.0.1.dist-info/licenses/LICENSE
fmu_sim2seis-0.0.1.dist-info/METADATA
fmu_sim2seis-0.0.1.dist-info/WHEEL
fmu_sim2seis-0.0.1.dist-info/entry_points.txt
fmu_sim2seis-0.0.1.dist-info/top_level.txt
fmu_sim2seis-0.0.1.dist-info/RECORD
