Metadata-Version: 2.4
Name: fmu-sim2seis
Version: 0.0.1
Summary: sim2seis
Author-email: Equinor <fg_fmu-atlas@equinor.com>
Project-URL: Homepage, https://github.com/equinor/fmu-sim2seis
Project-URL: Repository, https://github.com/equinor/fmu-sim2seis
Keywords: energy,subsurface,seismic,scientific,engineering
Classifier: Intended Audience :: Science/Research
Classifier: Topic :: Scientific/Engineering
Classifier: Topic :: Scientific/Engineering :: Physics
Classifier: Topic :: Software Development :: Libraries
Classifier: Topic :: Utilities
Classifier: Operating System :: POSIX :: Linux
Classifier: Programming Language :: Python :: 3.8
Classifier: Programming Language :: Python :: 3.9
Classifier: Programming Language :: Python :: 3.10
Classifier: Programming Language :: Python :: 3.11
Classifier: Natural Language :: English
Classifier: License :: OSI Approved :: GNU General Public License v3 (GPLv3)
Requires-Python: >=3.8
License-File: LICENSE
Requires-Dist: numpy>=1.24.3
Requires-Dist: pandas>=2.0.2
Requires-Dist: xtgeo>=3.7.1
Requires-Dist: fmu-tools>=1.16.0
Requires-Dist: fmu-config
Requires-Dist: fmu-dataio
Requires-Dist: fmu-pem
Requires-Dist: pydantic
Requires-Dist: ert
Requires-Dist: seismic-forward
Requires-Dist: si4ti
Provides-Extra: tests
Requires-Dist: mypy; extra == "tests"
Requires-Dist: pytest; extra == "tests"
Requires-Dist: pytest-cov; extra == "tests"
Requires-Dist: pytest-xdist; extra == "tests"
Requires-Dist: ruff; extra == "tests"
Provides-Extra: docs
Requires-Dist: autoapi; extra == "docs"
Requires-Dist: sphinx; extra == "docs"
Requires-Dist: sphinx-argparse; extra == "docs"
Requires-Dist: sphinx-autodoc-typehints; extra == "docs"
Requires-Dist: sphinx-copybutton; extra == "docs"
Requires-Dist: sphinx-togglebutton; extra == "docs"
Requires-Dist: sphinx_rtd_theme; extra == "docs"
Dynamic: license-file
